<annotation>
	<folder></folder>
	<filename>dd6b5c3cb2d7e77f38f1dfeb2bff0431_jpg.rf.9a8ea23dbdf192fee0434dbb0eb0f22c.jpg</filename>
	<path>dd6b5c3cb2d7e77f38f1dfeb2bff0431_jpg.rf.9a8ea23dbdf192fee0434dbb0eb0f22c.jpg</path>
	<source>
		<database>roboflow.ai</database>
	</source>
	<size>
		<width>416</width>
		<height>416</height>
		<depth>3</depth>
	</size>
	<segmented>0</segmented>
	<object>
		<name>black-queen</name>
		<pose>Unspecified</pose>
		<truncated>0</truncated>
		<difficult>0</difficult>
		<occluded>0</occluded>
		<bndbox>
			<xmin>315</xmin>
			<xmax>344</xmax>
			<ymin>98</ymin>
			<ymax>168</ymax>
		</bndbox>
	</object>
	<object>
		<name>black-king</name>
		<pose>Unspecified</pose>
		<truncated>0</truncated>
		<difficult>0</difficult>
		<occluded>0</occluded>
		<bndbox>
			<xmin>318</xmin>
			<xmax>351</xmax>
			<ymin>125</ymin>
			<ymax>205</ymax>
		</bndbox>
	</object>
	<object>
		<name>black-bishop</name>
		<pose>Unspecified</pose>
		<truncated>0</truncated>
		<difficult>0</difficult>
		<occluded>0</occluded>
		<bndbox>
			<xmin>307</xmin>
			<xmax>326</xmax>
			<ymin>67</ymin>
			<ymax>124</ymax>
		</bndbox>
	</object>
	<object>
		<name>black-bishop</name>
		<pose>Unspecified</pose>
		<truncated>0</truncated>
		<difficult>0</difficult>
		<occluded>0</occluded>
		<bndbox>
			<xmin>327</xmin>
			<xmax>355</xmax>
			<ymin>192</ymin>
			<ymax>251</ymax>
		</bndbox>
	</object>
	<object>
		<name>black-knight</name>
		<pose>Unspecified</pose>
		<truncated>0</truncated>
		<difficult>0</difficult>
		<occluded>0</occluded>
		<bndbox>
			<xmin>300</xmin>
			<xmax>324</xmax>
			<ymin>34</ymin>
			<ymax>89</ymax>
		</bndbox>
	</object>
	<object>
		<name>black-knight</name>
		<pose>Unspecified</pose>
		<truncated>0</truncated>
		<difficult>0</difficult>
		<occluded>0</occluded>
		<bndbox>
			<xmin>334</xmin>
			<xmax>367</xmax>
			<ymin>245</ymin>
			<ymax>301</ymax>
		</bndbox>
	</object>
	<object>
		<name>black-rook</name>
		<pose>Unspecified</pose>
		<truncated>0</truncated>
		<difficult>0</difficult>
		<occluded>0</occluded>
		<bndbox>
			<xmin>301</xmin>
			<xmax>323</xmax>
			<ymin>11</ymin>
			<ymax>57</ymax>
		</bndbox>
	</object>
	<object>
		<name>black-rook</name>
		<pose>Unspecified</pose>
		<truncated>0</truncated>
		<difficult>0</difficult>
		<occluded>0</occluded>
		<bndbox>
			<xmin>341</xmin>
			<xmax>372</xmax>
			<ymin>299</ymin>
			<ymax>356</ymax>
		</bndbox>
	</object>
	<object>
		<name>black-pawn</name>
		<pose>Unspecified</pose>
		<truncated>0</truncated>
		<difficult>0</difficult>
		<occluded>0</occluded>
		<bndbox>
			<xmin>267</xmin>
			<xmax>285</xmax>
			<ymin>10</ymin>
			<ymax>52</ymax>
		</bndbox>
	</object>
	<object>
		<name>black-pawn</name>
		<pose>Unspecified</pose>
		<truncated>0</truncated>
		<difficult>0</difficult>
		<occluded>0</occluded>
		<bndbox>
			<xmin>269</xmin>
			<xmax>287</xmax>
			<ymin>45</ymin>
			<ymax>87</ymax>
		</bndbox>
	</object>
	<object>
		<name>black-pawn</name>
		<pose>Unspecified</pose>
		<truncated>0</truncated>
		<difficult>0</difficult>
		<occluded>0</occluded>
		<bndbox>
			<xmin>275</xmin>
			<xmax>292</xmax>
			<ymin>81</ymin>
			<ymax>123</ymax>
		</bndbox>
	</object>
	<object>
		<name>black-pawn</name>
		<pose>Unspecified</pose>
		<truncated>0</truncated>
		<difficult>0</difficult>
		<occluded>0</occluded>
		<bndbox>
			<xmin>278</xmin>
			<xmax>297</xmax>
			<ymin>116</ymin>
			<ymax>160</ymax>
		</bndbox>
	</object>
	<object>
		<name>black-pawn</name>
		<pose>Unspecified</pose>
		<truncated>0</truncated>
		<difficult>0</difficult>
		<occluded>0</occluded>
		<bndbox>
			<xmin>283</xmin>
			<xmax>304</xmax>
			<ymin>157</ymin>
			<ymax>201</ymax>
		</bndbox>
	</object>
	<object>
		<name>black-pawn</name>
		<pose>Unspecified</pose>
		<truncated>0</truncated>
		<difficult>0</difficult>
		<occluded>0</occluded>
		<bndbox>
			<xmin>289</xmin>
			<xmax>310</xmax>
			<ymin>203</ymin>
			<ymax>247</ymax>
		</bndbox>
	</object>
	<object>
		<name>black-pawn</name>
		<pose>Unspecified</pose>
		<truncated>0</truncated>
		<difficult>0</difficult>
		<occluded>0</occluded>
		<bndbox>
			<xmin>293</xmin>
			<xmax>317</xmax>
			<ymin>250</ymin>
			<ymax>296</ymax>
		</bndbox>
	</object>
	<object>
		<name>black-pawn</name>
		<pose>Unspecified</pose>
		<truncated>0</truncated>
		<difficult>0</difficult>
		<occluded>0</occluded>
		<bndbox>
			<xmin>300</xmin>
			<xmax>323</xmax>
			<ymin>299</ymin>
			<ymax>349</ymax>
		</bndbox>
	</object>
	<object>
		<name>white-queen</name>
		<pose>Unspecified</pose>
		<truncated>0</truncated>
		<difficult>0</difficult>
		<occluded>0</occluded>
		<bndbox>
			<xmin>56</xmin>
			<xmax>83</xmax>
			<ymin>81</ymin>
			<ymax>155</ymax>
		</bndbox>
	</object>
	<object>
		<name>white-king</name>
		<pose>Unspecified</pose>
		<truncated>0</truncated>
		<difficult>0</difficult>
		<occluded>0</occluded>
		<bndbox>
			<xmin>49</xmin>
			<xmax>78</xmax>
			<ymin>112</ymin>
			<ymax>197</ymax>
		</bndbox>
	</object>
	<object>
		<name>white-bishop</name>
		<pose>Unspecified</pose>
		<truncated>0</truncated>
		<difficult>0</difficult>
		<occluded>0</occluded>
		<bndbox>
			<xmin>61</xmin>
			<xmax>83</xmax>
			<ymin>54</ymin>
			<ymax>113</ymax>
		</bndbox>
	</object>
	<object>
		<name>white-bishop</name>
		<pose>Unspecified</pose>
		<truncated>0</truncated>
		<difficult>0</difficult>
		<occluded>0</occluded>
		<bndbox>
			<xmin>45</xmin>
			<xmax>70</xmax>
			<ymin>179</ymin>
			<ymax>237</ymax>
		</bndbox>
	</object>
	<object>
		<name>white-knight</name>
		<pose>Unspecified</pose>
		<truncated>0</truncated>
		<difficult>0</difficult>
		<occluded>0</occluded>
		<bndbox>
			<xmin>66</xmin>
			<xmax>91</xmax>
			<ymin>23</ymin>
			<ymax>79</ymax>
		</bndbox>
	</object>
	<object>
		<name>white-knight</name>
		<pose>Unspecified</pose>
		<truncated>0</truncated>
		<difficult>0</difficult>
		<occluded>0</occluded>
		<bndbox>
			<xmin>46</xmin>
			<xmax>76</xmax>
			<ymin>228</ymin>
			<ymax>290</ymax>
		</bndbox>
	</object>
	<object>
		<name>white-rook</name>
		<pose>Unspecified</pose>
		<truncated>0</truncated>
		<difficult>0</difficult>
		<occluded>0</occluded>
		<bndbox>
			<xmin>69</xmin>
			<xmax>90</xmax>
			<ymin>3</ymin>
			<ymax>42</ymax>
		</bndbox>
	</object>
	<object>
		<name>white-rook</name>
		<pose>Unspecified</pose>
		<truncated>0</truncated>
		<difficult>0</difficult>
		<occluded>0</occluded>
		<bndbox>
			<xmin>36</xmin>
			<xmax>66</xmax>
			<ymin>291</ymin>
			<ymax>351</ymax>
		</bndbox>
	</object>
	<object>
		<name>white-pawn</name>
		<pose>Unspecified</pose>
		<truncated>0</truncated>
		<difficult>0</difficult>
		<occluded>0</occluded>
		<bndbox>
			<xmin>103</xmin>
			<xmax>121</xmax>
			<ymin>5</ymin>
			<ymax>43</ymax>
		</bndbox>
	</object>
	<object>
		<name>white-pawn</name>
		<pose>Unspecified</pose>
		<truncated>0</truncated>
		<difficult>0</difficult>
		<occluded>0</occluded>
		<bndbox>
			<xmin>102</xmin>
			<xmax>120</xmax>
			<ymin>37</ymin>
			<ymax>77</ymax>
		</bndbox>
	</object>
	<object>
		<name>white-pawn</name>
		<pose>Unspecified</pose>
		<truncated>0</truncated>
		<difficult>0</difficult>
		<occluded>0</occluded>
		<bndbox>
			<xmin>102</xmin>
			<xmax>119</xmax>
			<ymin>73</ymin>
			<ymax>116</ymax>
		</bndbox>
	</object>
	<object>
		<name>white-pawn</name>
		<pose>Unspecified</pose>
		<truncated>0</truncated>
		<difficult>0</difficult>
		<occluded>0</occluded>
		<bndbox>
			<xmin>99</xmin>
			<xmax>118</xmax>
			<ymin>109</ymin>
			<ymax>152</ymax>
		</bndbox>
	</object>
	<object>
		<name>white-pawn</name>
		<pose>Unspecified</pose>
		<truncated>0</truncated>
		<difficult>0</difficult>
		<occluded>0</occluded>
		<bndbox>
			<xmin>100</xmin>
			<xmax>119</xmax>
			<ymin>153</ymin>
			<ymax>197</ymax>
		</bndbox>
	</object>
	<object>
		<name>white-pawn</name>
		<pose>Unspecified</pose>
		<truncated>0</truncated>
		<difficult>0</difficult>
		<occluded>0</occluded>
		<bndbox>
			<xmin>94</xmin>
			<xmax>115</xmax>
			<ymin>198</ymin>
			<ymax>244</ymax>
		</bndbox>
	</object>
	<object>
		<name>white-pawn</name>
		<pose>Unspecified</pose>
		<truncated>0</truncated>
		<difficult>0</difficult>
		<occluded>0</occluded>
		<bndbox>
			<xmin>93</xmin>
			<xmax>115</xmax>
			<ymin>243</ymin>
			<ymax>289</ymax>
		</bndbox>
	</object>
	<object>
		<name>white-pawn</name>
		<pose>Unspecified</pose>
		<truncated>0</truncated>
		<difficult>0</difficult>
		<occluded>0</occluded>
		<bndbox>
			<xmin>87</xmin>
			<xmax>112</xmax>
			<ymin>296</ymin>
			<ymax>343</ymax>
		</bndbox>
	</object>
</annotation>
